sqlformater-1.0.11.dist-info/METADATA
sqlformater-1.0.11.dist-info/WHEEL
sqlformater-1.0.11.dist-info/entry_points.txt
sqlformater-1.0.11.dist-info/license_files/LICENSE
LICENSE
README.md
sqlformater/__init__.py
sqlformater/sqlformater.cp312-win_amd64.pyd
sqlformater-1.0.11.dist-info/RECORD
