Metadata-Version: 2.1
Name: sqlformater
Version: 1.0.11
License-File: LICENSE
Summary: Formater SQL written in Rust
Author: LugolBis
License: GPL-3.0-or-later
Project-URL: Repository, https://github.com/LugolBis/sqlformater
